django_test_without_migrations-0.2.dist-info/DESCRIPTION.rst
django_test_without_migrations-0.2.dist-info/METADATA
django_test_without_migrations-0.2.dist-info/metadata.json
django_test_without_migrations-0.2.dist-info/RECORD
django_test_without_migrations-0.2.dist-info/top_level.txt
django_test_without_migrations-0.2.dist-info/WHEEL
django_test_without_migrations-0.2.dist-info/zip-safe
test_without_migrations/__init__.py
test_without_migrations/management/__init__.py
test_without_migrations/management/commands/__init__.py
test_without_migrations/management/commands/test.py
