Metadata-Version: 2.0
Name: django-test-without-migrations
Version: 0.2
Summary: Disable migrations when running your Django tests.
Home-page: http://github.com/henriquebastos/django-test-without-migrations/
Author: Henrique Bastos
Author-email: henrique@bastos.net
License: MIT
Platform: any
Classifier: Development Status :: 5 - Production/Stable
Classifier: Framework :: Django
Classifier: Intended Audience :: Developers
Classifier: License :: OSI Approved :: MIT License
Classifier: Natural Language :: English
Classifier: Operating System :: OS Independent
Classifier: Programming Language :: Python
Classifier: Programming Language :: Python :: 2.7
Classifier: Programming Language :: Python :: 3
Classifier: Topic :: Software Development :: Libraries
